hammer_irview/__init__.py
hammer_irview/irv/__init__.py
hammer_irview/irv/app.py
hammer_irview/irv/mainwindow.py
hammer_irview/irv/pluginmgr.py
hammer_irview/irv/hierarchical/__init__.py
hammer_irview/irv/hierarchical/lef.py
hammer_irview/irv/hierarchical/placement_constraints.py
hammer_irview/irv/hierarchical/verilog_module.py
hammer_irview/irv/hierarchical/yml_loader.py
hammer_irview/irv/models/__init__.py
hammer_irview/irv/models/hierarchy.py
hammer_irview/irv/models/verilog_module.py
hammer_irview/irv/widgets/__init__.py
hammer_irview/irv/widgets/loading_modal.py
hammer_irview/irv/widgets/mplcanvas.py
hammer_irview/irv/widgets/mplzoompan.py
hammer_irview/irv/widgets/overlay.py
hammer_irview/irv/widgets/statusbar_mgr.py
hammer_irview/ui/hammer.gif
hammer_irview/ui/icon-aligned.jpg
hammer_irview/ui/icon-misaligned.png
hammer_irview/ui/loading.svg
hammer_irview/ui/main.ui
hammer_irview-0.1.0.dist-info/licenses/LICENSE
hammer_irview-0.1.0.dist-info/METADATA
hammer_irview-0.1.0.dist-info/WHEEL
hammer_irview-0.1.0.dist-info/top_level.txt
hammer_irview-0.1.0.dist-info/RECORD
